keyboard_listener/__init__.py
keyboard_listener-0.0.7.dist-info/LICENSE
keyboard_listener-0.0.7.dist-info/METADATA
keyboard_listener-0.0.7.dist-info/WHEEL
keyboard_listener-0.0.7.dist-info/top_level.txt
keyboard_listener-0.0.7.dist-info/RECORD
