Metadata-Version: 2.1
Name: keyboard-listener
Version: 0.0.7
Summary: A keyboard listener that allows for custom combinations and keywords to trigger custom functions
Home-page: https://github.com/dibsonthis/keyboard_listener
Author: Adib Attie
Author-email: adib.attie33@gmail.com
License: UNKNOWN
Platform: UNKNOWN
Classifier: Programming Language :: Python :: 3
Classifier: License :: OSI Approved :: MIT License
Classifier: Operating System :: OS Independent
Requires-Python: >=3.6
